nftables.py
ansibleguy_nftables-1.0.2.post1.dist-info/METADATA
ansibleguy_nftables-1.0.2.post1.dist-info/WHEEL
ansibleguy_nftables-1.0.2.post1.dist-info/top_level.txt
ansibleguy_nftables-1.0.2.post1.dist-info/RECORD
